<?xml version="1.0" encoding="UTF-8" standalone="no"?><Patient id="jd000001"><first_name>John</first_name><last_name>Doe</last_name><age>28</age><phone>4058698576</phone><address>oklahoma</address><email>kjsdnkc@gmail.com</email><clump_thickness>5</clump_thickness><uniformity_cell_size>1</uniformity_cell_size><uniformity_cell_shape>1</uniformity_cell_shape><marginal_adhesion>1</marginal_adhesion><single_epithelial_cell_size>2</single_epithelial_cell_size><bare_nuclei>1</bare_nuclei><bland_chromatin>2</bland_chromatin><normal_nucleoli>2</normal_nucleoli><mitoses>1</mitoses><class>2</class></Patient>